ansqlite/__init__.py
ansqlite/database.py
ansqlite/exceptions.py
ansqlite/schema.py
ansqlite/utils.py
ansqlite-0.4.2.dist-info/LICENSE
ansqlite-0.4.2.dist-info/METADATA
ansqlite-0.4.2.dist-info/WHEEL
ansqlite-0.4.2.dist-info/top_level.txt
ansqlite-0.4.2.dist-info/RECORD
