Metadata-Version: 2.1
Name: ansqlite
Version: 0.4.2
Summary: Helper module for simple sqlite3 use cases
Author-email: Antti Nilsson <muut.py@antion.fi>
Classifier: Programming Language :: Python :: 3
Classifier: License :: OSI Approved :: MIT License
Classifier: Operating System :: OS Independent
Requires-Python: >=3.7
License-File: LICENSE
Requires-Dist: anlogger
Requires-Dist: pydantic
